{
  "today_camp": [
    {
      "campaign": "Feminnita | Revenda Sul+Sudeste | VENDAS",
      "adset": null,
      "ad": null,
      "spend": 24.2,
      "impr": 729,
      "clicks": 25,
      "ctr": 3.43,
      "cpc": 0.97,
      "cpm": 33.2,
      "reach": 546,
      "freq": 1.34,
      "lpv": 12,
      "vc": 24,
      "atc": 1,
      "ic": 0,
      "purch": 0,
      "cpa_purch": 0,
      "cpa_atc": 24.2,
      "cpa_lpv": 2.02,
      "rev": 0,
      "roas": 0
    },
    {
      "campaign": "Feminnita | Remarketing | VENDAS",
      "adset": null,
      "ad": null,
      "spend": 37.89,
      "impr": 873,
      "clicks": 42,
      "ctr": 4.81,
      "cpc": 0.9,
      "cpm": 43.4,
      "reach": 596,
      "freq": 1.46,
      "lpv": 36,
      "vc": 27,
      "atc": 3,
      "ic": 4,
      "purch": 3,
      "cpa_purch": 12.63,
      "cpa_atc": 12.63,
      "cpa_lpv": 1.05,
      "rev": 636.53,
      "roas": 16.8
    }
  ],
  "l7_camp": [
    {
      "campaign": "Feminnita | Revenda Sul+Sudeste | VENDAS",
      "adset": null,
      "ad": null,
      "spend": 568.12,
      "impr": 18703,
      "clicks": 885,
      "ctr": 4.73,
      "cpc": 0.64,
      "cpm": 30.38,
      "reach": 7685,
      "freq": 2.43,
      "lpv": 459,
      "vc": 829,
      "atc": 69,
      "ic": 23,
      "purch": 9,
      "cpa_purch": 63.12,
      "cpa_atc": 8.23,
      "cpa_lpv": 1.24,
      "rev": 3223.32,
      "roas": 5.67
    },
    {
      "campaign": "Feminnita | Remarketing | VENDAS",
      "adset": null,
      "ad": null,
      "spend": 728.76,
      "impr": 19891,
      "clicks": 965,
      "ctr": 4.85,
      "cpc": 0.76,
      "cpm": 36.64,
      "reach": 7593,
      "freq": 2.62,
      "lpv": 479,
      "vc": 880,
      "atc": 89,
      "ic": 15,
      "purch": 5,
      "cpa_purch": 145.75,
      "cpa_atc": 8.19,
      "cpa_lpv": 1.52,
      "rev": 3033.98,
      "roas": 4.16
    }
  ],
  "today_adset": [
    {
      "campaign": "Feminnita | Revenda Sul+Sudeste | VENDAS",
      "adset": "Feminnita | Sul+Sudeste | Mulheres 25-55 | Revenda",
      "ad": null,
      "spend": 17.21,
      "impr": 527,
      "clicks": 16,
      "ctr": 3.04,
      "cpc": 1.08,
      "cpm": 32.66,
      "reach": 448,
      "freq": 1.18,
      "lpv": 9,
      "vc": 3,
      "atc": 0,
      "ic": 0,
      "purch": 0,
      "cpa_purch": 0,
      "cpa_atc": 0,
      "cpa_lpv": 1.91,
      "rev": 0,
      "roas": 0
    },
    {
      "campaign": "Feminnita | Remarketing | VENDAS",
      "adset": "Novo conjunto de anúncios de Vendas",
      "ad": null,
      "spend": 6.29,
      "impr": 140,
      "clicks": 12,
      "ctr": 8.57,
      "cpc": 0.52,
      "cpm": 44.93,
      "reach": 120,
      "freq": 1.17,
      "lpv": 7,
      "vc": 8,
      "atc": 3,
      "ic": 4,
      "purch": 3,
      "cpa_purch": 2.1,
      "cpa_atc": 2.1,
      "cpa_lpv": 0.9,
      "rev": 636.53,
      "roas": 101.2
    },
    {
      "campaign": "Feminnita | Revenda Sul+Sudeste | VENDAS",
      "adset": "Feminnita | Brasil Inteiro | Mulheres 25-55 | Revenda",
      "ad": null,
      "spend": 6.99,
      "impr": 202,
      "clicks": 9,
      "ctr": 4.46,
      "cpc": 0.78,
      "cpm": 34.6,
      "reach": 150,
      "freq": 1.35,
      "lpv": 3,
      "vc": 21,
      "atc": 1,
      "ic": 0,
      "purch": 0,
      "cpa_purch": 0,
      "cpa_atc": 6.99,
      "cpa_lpv": 2.33,
      "rev": 0,
      "roas": 0
    },
    {
      "campaign": "Feminnita | Remarketing | VENDAS",
      "adset": "04 | IG & FB | Novos Públicos RMK | Sul & Sudeste",
      "ad": null,
      "spend": 31.6,
      "impr": 733,
      "clicks": 30,
      "ctr": 4.09,
      "cpc": 1.05,
      "cpm": 43.11,
      "reach": 506,
      "freq": 1.45,
      "lpv": 29,
      "vc": 19,
      "atc": 0,
      "ic": 0,
      "purch": 0,
      "cpa_purch": 0,
      "cpa_atc": 0,
      "cpa_lpv": 1.09,
      "rev": 0,
      "roas": 0
    }
  ],
  "l7_adset": [
    {
      "campaign": "Feminnita | Revenda Sul+Sudeste | VENDAS",
      "adset": "Feminnita | Sul+Sudeste | Mulheres 25-55 | Revenda",
      "ad": null,
      "spend": 404.25,
      "impr": 13244,
      "clicks": 638,
      "ctr": 4.82,
      "cpc": 0.63,
      "cpm": 30.52,
      "reach": 6202,
      "freq": 2.14,
      "lpv": 337,
      "vc": 587,
      "atc": 49,
      "ic": 12,
      "purch": 4,
      "cpa_purch": 101.06,
      "cpa_atc": 8.25,
      "cpa_lpv": 1.2,
      "rev": 1425.56,
      "roas": 3.53
    },
    {
      "campaign": "Feminnita | Remarketing | VENDAS",
      "adset": "Novo conjunto de anúncios de Vendas",
      "ad": null,
      "spend": 90.8,
      "impr": 2180,
      "clicks": 119,
      "ctr": 5.46,
      "cpc": 0.76,
      "cpm": 41.65,
      "reach": 1253,
      "freq": 1.74,
      "lpv": 50,
      "vc": 61,
      "atc": 8,
      "ic": 0,
      "purch": 0,
      "cpa_purch": 0,
      "cpa_atc": 11.35,
      "cpa_lpv": 1.82,
      "rev": 0,
      "roas": 0
    },
    {
      "campaign": "Feminnita | Revenda Sul+Sudeste | VENDAS",
      "adset": "Feminnita | Brasil Inteiro | Mulheres 25-55 | Revenda",
      "ad": null,
      "spend": 163.87,
      "impr": 5459,
      "clicks": 247,
      "ctr": 4.52,
      "cpc": 0.66,
      "cpm": 30.02,
      "reach": 2925,
      "freq": 1.87,
      "lpv": 122,
      "vc": 242,
      "atc": 20,
      "ic": 11,
      "purch": 5,
      "cpa_purch": 32.77,
      "cpa_atc": 8.19,
      "cpa_lpv": 1.34,
      "rev": 1797.76,
      "roas": 10.97
    },
    {
      "campaign": "Feminnita | Remarketing | VENDAS",
      "adset": "04 | IG & FB | Novos Públicos RMK | Sul & Sudeste",
      "ad": null,
      "spend": 637.96,
      "impr": 17711,
      "clicks": 846,
      "ctr": 4.78,
      "cpc": 0.75,
      "cpm": 36.02,
      "reach": 7072,
      "freq": 2.5,
      "lpv": 429,
      "vc": 819,
      "atc": 81,
      "ic": 15,
      "purch": 5,
      "cpa_purch": 127.59,
      "cpa_atc": 7.88,
      "cpa_lpv": 1.49,
      "rev": 3033.98,
      "roas": 4.76
    }
  ],
  "today_ad": [
    {
      "campaign": "Feminnita | Remarketing | VENDAS",
      "adset": "Novo conjunto de anúncios de Vendas",
      "ad": "Remarketing Vendas - Banner Atacado",
      "spend": 6.29,
      "impr": 140,
      "clicks": 12,
      "ctr": 8.57,
      "cpc": 0.52,
      "cpm": 44.93,
      "reach": 120,
      "freq": 1.17,
      "lpv": 7,
      "vc": 8,
      "atc": 3,
      "ic": 4,
      "purch": 3,
      "cpa_purch": 2.1,
      "cpa_atc": 2.1,
      "cpa_lpv": 0.9,
      "rev": 636.53,
      "roas": 101.2
    },
    {
      "campaign": "Feminnita | Revenda Sul+Sudeste | VENDAS",
      "adset": "Feminnita | Sul+Sudeste | Mulheres 25-55 | Revenda",
      "ad": "Revenda | Banner Bolinhas",
      "spend": 17.21,
      "impr": 527,
      "clicks": 16,
      "ctr": 3.04,
      "cpc": 1.08,
      "cpm": 32.66,
      "reach": 448,
      "freq": 1.18,
      "lpv": 9,
      "vc": 3,
      "atc": 0,
      "ic": 0,
      "purch": 0,
      "cpa_purch": 0,
      "cpa_atc": 0,
      "cpa_lpv": 1.91,
      "rev": 0,
      "roas": 0
    },
    {
      "campaign": "Feminnita | Revenda Sul+Sudeste | VENDAS",
      "adset": "Feminnita | Brasil Inteiro | Mulheres 25-55 | Revenda",
      "ad": "Anúncio — FORNECEDOR QUE GIRA ESTOQUE",
      "spend": 0.29,
      "impr": 8,
      "clicks": 0,
      "ctr": 0.0,
      "cpc": 0.0,
      "cpm": 36.25,
      "reach": 6,
      "freq": 1.33,
      "lpv": 0,
      "vc": 0,
      "atc": 0,
      "ic": 0,
      "purch": 0,
      "cpa_purch": 0,
      "cpa_atc": 0,
      "cpa_lpv": 0,
      "rev": 0,
      "roas": 0
    },
    {
      "campaign": "Feminnita | Revenda Sul+Sudeste | VENDAS",
      "adset": "Feminnita | Brasil Inteiro | Mulheres 25-55 | Revenda",
      "ad": "Revenda | Banner Bolinhas",
      "spend": 5.96,
      "impr": 180,
      "clicks": 6,
      "ctr": 3.33,
      "cpc": 0.99,
      "cpm": 33.11,
      "reach": 136,
      "freq": 1.32,
      "lpv": 0,
      "vc": 18,
      "atc": 1,
      "ic": 0,
      "purch": 0,
      "cpa_purch": 0,
      "cpa_atc": 5.96,
      "cpa_lpv": 0,
      "rev": 0,
      "roas": 0
    },
    {
      "campaign": "Feminnita | Revenda Sul+Sudeste | VENDAS",
      "adset": "Feminnita | Brasil Inteiro | Mulheres 25-55 | Revenda",
      "ad": "Revenda | Banner Azul Royal",
      "spend": 0.74,
      "impr": 14,
      "clicks": 3,
      "ctr": 21.43,
      "cpc": 0.25,
      "cpm": 52.86,
      "reach": 14,
      "freq": 1.0,
      "lpv": 3,
      "vc": 3,
      "atc": 0,
      "ic": 0,
      "purch": 0,
      "cpa_purch": 0,
      "cpa_atc": 0,
      "cpa_lpv": 0.25,
      "rev": 0,
      "roas": 0
    },
    {
      "campaign": "Feminnita | Remarketing | VENDAS",
      "adset": "04 | IG & FB | Novos Públicos RMK | Sul & Sudeste",
      "ad": "Remarketing Vendas - Banner Atacado",
      "spend": 31.6,
      "impr": 733,
      "clicks": 30,
      "ctr": 4.09,
      "cpc": 1.05,
      "cpm": 43.11,
      "reach": 506,
      "freq": 1.45,
      "lpv": 29,
      "vc": 19,
      "atc": 0,
      "ic": 0,
      "purch": 0,
      "cpa_purch": 0,
      "cpa_atc": 0,
      "cpa_lpv": 1.09,
      "rev": 0,
      "roas": 0
    }
  ],
  "l7_ad": [
    {
      "campaign": "Feminnita | Remarketing | VENDAS",
      "adset": "Novo conjunto de anúncios de Vendas",
      "ad": "Remarketing Vendas - Banner Atacado",
      "spend": 90.8,
      "impr": 2180,
      "clicks": 119,
      "ctr": 5.46,
      "cpc": 0.76,
      "cpm": 41.65,
      "reach": 1253,
      "freq": 1.74,
      "lpv": 50,
      "vc": 61,
      "atc": 8,
      "ic": 0,
      "purch": 0,
      "cpa_purch": 0,
      "cpa_atc": 11.35,
      "cpa_lpv": 1.82,
      "rev": 0,
      "roas": 0
    },
    {
      "campaign": "Feminnita | Revenda Sul+Sudeste | VENDAS",
      "adset": "Feminnita | Sul+Sudeste | Mulheres 25-55 | Revenda",
      "ad": "Revenda | Banner Azul Royal",
      "spend": 12.04,
      "impr": 404,
      "clicks": 16,
      "ctr": 3.96,
      "cpc": 0.75,
      "cpm": 29.8,
      "reach": 315,
      "freq": 1.28,
      "lpv": 8,
      "vc": 13,
      "atc": 7,
      "ic": 0,
      "purch": 0,
      "cpa_purch": 0,
      "cpa_atc": 1.72,
      "cpa_lpv": 1.5,
      "rev": 0,
      "roas": 0
    },
    {
      "campaign": "Feminnita | Revenda Sul+Sudeste | VENDAS",
      "adset": "Feminnita | Sul+Sudeste | Mulheres 25-55 | Revenda",
      "ad": "Revenda | Banner Bolinhas",
      "spend": 357.99,
      "impr": 11818,
      "clicks": 593,
      "ctr": 5.02,
      "cpc": 0.6,
      "cpm": 30.29,
      "reach": 5981,
      "freq": 1.98,
      "lpv": 312,
      "vc": 419,
      "atc": 25,
      "ic": 9,
      "purch": 3,
      "cpa_purch": 119.33,
      "cpa_atc": 14.32,
      "cpa_lpv": 1.15,
      "rev": 994.01,
      "roas": 2.78
    },
    {
      "campaign": "Feminnita | Revenda Sul+Sudeste | VENDAS",
      "adset": "Feminnita | Sul+Sudeste | Mulheres 25-55 | Revenda",
      "ad": "Anúncio — FORNECEDOR QUE GIRA ESTOQUE",
      "spend": 12.14,
      "impr": 314,
      "clicks": 10,
      "ctr": 3.18,
      "cpc": 1.21,
      "cpm": 38.66,
      "reach": 225,
      "freq": 1.4,
      "lpv": 6,
      "vc": 14,
      "atc": 0,
      "ic": 0,
      "purch": 0,
      "cpa_purch": 0,
      "cpa_atc": 0,
      "cpa_lpv": 2.02,
      "rev": 0,
      "roas": 0
    },
    {
      "campaign": "Feminnita | Revenda Sul+Sudeste | VENDAS",
      "adset": "Feminnita | Sul+Sudeste | Mulheres 25-55 | Revenda",
      "ad": "Anúncio — FORNECEDOR QUE GIRA ESTOQUE",
      "spend": 10.66,
      "impr": 348,
      "clicks": 11,
      "ctr": 3.16,
      "cpc": 0.97,
      "cpm": 30.63,
      "reach": 277,
      "freq": 1.26,
      "lpv": 7,
      "vc": 10,
      "atc": 2,
      "ic": 0,
      "purch": 0,
      "cpa_purch": 0,
      "cpa_atc": 5.33,
      "cpa_lpv": 1.52,
      "rev": 0,
      "roas": 0
    },
    {
      "campaign": "Feminnita | Revenda Sul+Sudeste | VENDAS",
      "adset": "Feminnita | Sul+Sudeste | Mulheres 25-55 | Revenda",
      "ad": "Anúncio — REUNIU AS AMIGAS E PAGOU PREÇO DE FÁBRICA",
      "spend": 7.57,
      "impr": 242,
      "clicks": 5,
      "ctr": 2.07,
      "cpc": 1.51,
      "cpm": 31.28,
      "reach": 165,
      "freq": 1.47,
      "lpv": 1,
      "vc": 4,
      "atc": 0,
      "ic": 0,
      "purch": 0,
      "cpa_purch": 0,
      "cpa_atc": 0,
      "cpa_lpv": 7.57,
      "rev": 0,
      "roas": 0
    },
    {
      "campaign": "Feminnita | Revenda Sul+Sudeste | VENDAS",
      "adset": "Feminnita | Sul+Sudeste | Mulheres 25-55 | Revenda",
      "ad": "Anúncio — Venda pijamas pelo WhatsApp sem sair de casa",
      "spend": 3.85,
      "impr": 118,
      "clicks": 3,
      "ctr": 2.54,
      "cpc": 1.28,
      "cpm": 32.63,
      "reach": 82,
      "freq": 1.44,
      "lpv": 3,
      "vc": 127,
      "atc": 15,
      "ic": 3,
      "purch": 1,
      "cpa_purch": 3.85,
      "cpa_atc": 0.26,
      "cpa_lpv": 1.28,
      "rev": 431.55,
      "roas": 112.09
    },
    {
      "campaign": "Feminnita | Revenda Sul+Sudeste | VENDAS",
      "adset": "Feminnita | Brasil Inteiro | Mulheres 25-55 | Revenda",
      "ad": "Anúncio — REUNIU AS AMIGAS E PAGOU PREÇO DE FÁBRICA",
      "spend": 5.86,
      "impr": 192,
      "clicks": 5,
      "ctr": 2.6,
      "cpc": 1.17,
      "cpm": 30.52,
      "reach": 138,
      "freq": 1.39,
      "lpv": 1,
      "vc": 0,
      "atc": 0,
      "ic": 0,
      "purch": 0,
      "cpa_purch": 0,
      "cpa_atc": 0,
      "cpa_lpv": 5.86,
      "rev": 0,
      "roas": 0
    },
    {
      "campaign": "Feminnita | Revenda Sul+Sudeste | VENDAS",
      "adset": "Feminnita | Brasil Inteiro | Mulheres 25-55 | Revenda",
      "ad": "Anúncio — FORNECEDOR QUE GIRA ESTOQUE",
      "spend": 6.65,
      "impr": 175,
      "clicks": 15,
      "ctr": 8.57,
      "cpc": 0.44,
      "cpm": 38.0,
      "reach": 131,
      "freq": 1.34,
      "lpv": 9,
      "vc": 12,
      "atc": 0,
      "ic": 0,
      "purch": 0,
      "cpa_purch": 0,
      "cpa_atc": 0,
      "cpa_lpv": 0.74,
      "rev": 0,
      "roas": 0
    },
    {
      "campaign": "Feminnita | Revenda Sul+Sudeste | VENDAS",
      "adset": "Feminnita | Brasil Inteiro | Mulheres 25-55 | Revenda",
      "ad": "Revenda | Banner Bolinhas",
      "spend": 129.69,
      "impr": 4411,
      "clicks": 205,
      "ctr": 4.65,
      "cpc": 0.63,
      "cpm": 29.4,
      "reach": 2689,
      "freq": 1.64,
      "lpv": 104,
      "vc": 178,
      "atc": 12,
      "ic": 8,
      "purch": 3,
      "cpa_purch": 43.23,
      "cpa_atc": 10.81,
      "cpa_lpv": 1.25,
      "rev": 928.65,
      "roas": 7.16
    },
    {
      "campaign": "Feminnita | Revenda Sul+Sudeste | VENDAS",
      "adset": "Feminnita | Brasil Inteiro | Mulheres 25-55 | Revenda",
      "ad": "Revenda | Banner Azul Royal",
      "spend": 13.53,
      "impr": 436,
      "clicks": 17,
      "ctr": 3.9,
      "cpc": 0.8,
      "cpm": 31.03,
      "reach": 328,
      "freq": 1.33,
      "lpv": 5,
      "vc": 50,
      "atc": 8,
      "ic": 3,
      "purch": 2,
      "cpa_purch": 6.76,
      "cpa_atc": 1.69,
      "cpa_lpv": 2.71,
      "rev": 869.11,
      "roas": 64.24
    },
    {
      "campaign": "Feminnita | Revenda Sul+Sudeste | VENDAS",
      "adset": "Feminnita | Brasil Inteiro | Mulheres 25-55 | Revenda",
      "ad": "Anúncio — Venda pijamas pelo WhatsApp sem sair de casa",
      "spend": 1.7,
      "impr": 45,
      "clicks": 1,
      "ctr": 2.22,
      "cpc": 1.7,
      "cpm": 37.78,
      "reach": 39,
      "freq": 1.15,
      "lpv": 1,
      "vc": 0,
      "atc": 0,
      "ic": 0,
      "purch": 0,
      "cpa_purch": 0,
      "cpa_atc": 0,
      "cpa_lpv": 1.7,
      "rev": 0,
      "roas": 0
    },
    {
      "campaign": "Feminnita | Revenda Sul+Sudeste | VENDAS",
      "adset": "Feminnita | Brasil Inteiro | Mulheres 25-55 | Revenda",
      "ad": "Anúncio — FORNECEDOR QUE GIRA ESTOQUE",
      "spend": 6.44,
      "impr": 200,
      "clicks": 4,
      "ctr": 2.0,
      "cpc": 1.61,
      "cpm": 32.2,
      "reach": 164,
      "freq": 1.22,
      "lpv": 2,
      "vc": 2,
      "atc": 0,
      "ic": 0,
      "purch": 0,
      "cpa_purch": 0,
      "cpa_atc": 0,
      "cpa_lpv": 3.22,
      "rev": 0,
      "roas": 0
    },
    {
      "campaign": "Feminnita | Remarketing | VENDAS",
      "adset": "04 | IG & FB | Novos Públicos RMK | Sul & Sudeste",
      "ad": "Remarketing Vendas - Banner Atacado",
      "spend": 613.26,
      "impr": 17256,
      "clicks": 833,
      "ctr": 4.83,
      "cpc": 0.74,
      "cpm": 35.54,
      "reach": 7011,
      "freq": 2.46,
      "lpv": 420,
      "vc": 787,
      "atc": 79,
      "ic": 14,
      "purch": 5,
      "cpa_purch": 122.65,
      "cpa_atc": 7.76,
      "cpa_lpv": 1.46,
      "rev": 3033.98,
      "roas": 4.95
    },
    {
      "campaign": "Feminnita | Remarketing | VENDAS",
      "adset": "04 | IG & FB | Novos Públicos RMK | Sul & Sudeste",
      "ad": "Remarketing Vendas - Banner Atacado — Cópia",
      "spend": 24.7,
      "impr": 455,
      "clicks": 13,
      "ctr": 2.86,
      "cpc": 1.9,
      "cpm": 54.29,
      "reach": 252,
      "freq": 1.81,
      "lpv": 9,
      "vc": 32,
      "atc": 2,
      "ic": 1,
      "purch": 0,
      "cpa_purch": 0,
      "cpa_atc": 12.35,
      "cpa_lpv": 2.74,
      "rev": 0,
      "roas": 0
    }
  ]
}